{
  "customers": [
    {
      "_id": "123456abc",
      "firstName": "John",
      "lastName": "Doe",
      "email": "jd@gmail.com",
      "address": {
        "zip": 1183,
        "city": "Budapest",
        "street": "Széchenyi u. 1/A."
      },
      "active": true,
      "phone": "+36301234567",
      "coupon": 235
    },
    {
      "_id": "123000abc",
      "firstName": "Jane",
      "lastName": "Doe",
      "email": "janed@gmail.com",
      "address": {
        "zip": 1115,
        "city": "Budapest",
        "street": "Kossuth u. 3."
      },
      "active": false,
      "phone": "+36301234500",
      "coupon": 200
    }
  ],
  "products": [
    {
      "_id": "987fgh",
      "name": "Mutsu",
      "category": "apple",
      "price": 300,
      "active": true,
      "description": "This is a green apple."
    },
    {
      "_id": "999fff",
      "name": "Bosc kobak",
      "category": "pear",
      "price": 350,
      "active": true,
      "description": "This is a delicious pear."
    }
  ],
  "orders": [
    {
      "_id": "246ace",
      "customerId": "123456abc",
      "productIds": [
        "987fgh",
        "999fff"
      ],
      "time": 1627700000000,
      "amount": "5000",
      "status": "new",
      "note": "Please call me before delivery."
    },
    {
      "_id": "246acc",
      "customerId": "123000abc",
      "productIds": [
        "987fgh"
      ],
      "time": 1626699947303,
      "amount": "3000",
      "status": "shipped"
    }
  ],
  "bills": [
    {
      "_id": "987654mnb",
      "orderId": "246ace",
      "time": 1626699947303,
      "status": "new"
    },
    {
      "_id": "980000aaa",
      "orderId": "246acc",
      "time": 1627700000000,
      "status": "paid"
    }
  ]
}
